alibabacloud_docmind_api20220729/__init__.py
alibabacloud_docmind_api20220729/client.py
alibabacloud_docmind_api20220729/models.py
alibabacloud_docmind_api20220729-1.2.1.dist-info/LICENSE
alibabacloud_docmind_api20220729-1.2.1.dist-info/METADATA
alibabacloud_docmind_api20220729-1.2.1.dist-info/WHEEL
alibabacloud_docmind_api20220729-1.2.1.dist-info/top_level.txt
alibabacloud_docmind_api20220729-1.2.1.dist-info/RECORD
